odoo/addons/l10n_it_website_portal_fatturapa_sale/README.rst
odoo/addons/l10n_it_website_portal_fatturapa_sale/__init__.py
odoo/addons/l10n_it_website_portal_fatturapa_sale/__manifest__.py
odoo/addons/l10n_it_website_portal_fatturapa_sale/i18n/it.po
odoo/addons/l10n_it_website_portal_fatturapa_sale/i18n/l10n_it_website_portal_fatturapa_sale.pot
odoo/addons/l10n_it_website_portal_fatturapa_sale/models/__init__.py
odoo/addons/l10n_it_website_portal_fatturapa_sale/models/company.py
odoo/addons/l10n_it_website_portal_fatturapa_sale/models/res_config_settings.py
odoo/addons/l10n_it_website_portal_fatturapa_sale/models/res_partner.py
odoo/addons/l10n_it_website_portal_fatturapa_sale/readme/CONTRIBUTORS.rst
odoo/addons/l10n_it_website_portal_fatturapa_sale/readme/DESCRIPTION.rst
odoo/addons/l10n_it_website_portal_fatturapa_sale/static/description/icon.png
odoo/addons/l10n_it_website_portal_fatturapa_sale/static/description/index.html
odoo/addons/l10n_it_website_portal_fatturapa_sale/static/src/js/payment_form.js
odoo/addons/l10n_it_website_portal_fatturapa_sale/static/src/js/portal.js
odoo/addons/l10n_it_website_portal_fatturapa_sale/static/src/js/signature_form.js
odoo/addons/l10n_it_website_portal_fatturapa_sale/views/assets.xml
odoo/addons/l10n_it_website_portal_fatturapa_sale/views/payment_templates.xml
odoo/addons/l10n_it_website_portal_fatturapa_sale/views/res_config_settings_view.xml
odoo12_addon_l10n_it_website_portal_fatturapa_sale-12.0.1.1.1.dist-info/METADATA
odoo12_addon_l10n_it_website_portal_fatturapa_sale-12.0.1.1.1.dist-info/WHEEL
odoo12_addon_l10n_it_website_portal_fatturapa_sale-12.0.1.1.1.dist-info/top_level.txt
odoo12_addon_l10n_it_website_portal_fatturapa_sale-12.0.1.1.1.dist-info/RECORD
